LICENSE
MANIFEST.in
README.md
requirements.txt
setup.cfg
setup.py
dialogflow_lite/__init__.py
dialogflow_lite/dialogflow.py
dialogflow_lite/status.py
dialogflow_lite.egg-info/PKG-INFO
dialogflow_lite.egg-info/SOURCES.txt
dialogflow_lite.egg-info/dependency_links.txt
dialogflow_lite.egg-info/requires.txt
dialogflow_lite.egg-info/top_level.txt