Metadata-Version: 1.1
Name: dialogflow-lite
Version: 0.0.6
Summary: A light-weight agent for Dialogflow.
Home-page: https://github.com/vkosuri/dialogflow-lite
Author: Mallikarjunarao Kosuri
Author-email: malli.kv2@gmail.com
License: MIT
Keywords: dialogflow,dialogflow-lite,api.ai,dialogflow python,bot,speech,voice
Platform: any
Classifier: Development Status :: 4 - Beta
Classifier: Intended Audience :: Developers
Classifier: License :: OSI Approved :: MIT License
Classifier: Environment :: Console
Classifier: Environment :: Web Environment
Classifier: Operating System :: OS Independent
Classifier: Topic :: Software Development :: Libraries :: Python Modules
Classifier: Topic :: Communications :: Chat
Classifier: Topic :: Internet
Classifier: Programming Language :: Python
Classifier: Programming Language :: Python :: 2.7
Classifier: Programming Language :: Python :: 3
Classifier: Programming Language :: Python :: 3.3
Classifier: Programming Language :: Python :: 3.4
Classifier: Programming Language :: Python :: 3.5
